setup.py
event_handler/__init__.py
event_handler.egg-info/PKG-INFO
event_handler.egg-info/SOURCES.txt
event_handler.egg-info/dependency_links.txt
event_handler.egg-info/top_level.txt
event_handler/events/__init__.py
event_handler/events/events.py
tests/__init__.py
tests/events/__init__.py
tests/events/events.py