Metadata-Version: 1.0
Name: event-handler
Version: 0.1.0
Summary: A simple event handler and dispatcher
Home-page: http://github.com/dlitvakb
Author: David Litvak
Author-email: david.litvakb@gmail.com
License: GPL v3
Keywords: Events Thrower Listener
Platform: UNKNOWN
